counter_assertion_property/design.sv
// Code your design here
//`timescale 1ns/ 1ps;
module counter8b (clk,rst_n,ld_en,updwn,en,datain,dataout);
  
  input clk, rst_n,ld_en,updwn,en;           
  input  [7:0] datain;
  output [7:0] dataout;
  reg    [7:0] sdataout;
  
  always @(posedge clk or negedge rst_n)
    begin
      if(!rst_n)
        sdataout=8'b0;
    else if(ld_en)
          sdataout=datain; 
    else if(!en)
          sdataout=sdataout;
    else if (updwn)
       	   sdataout=sdataout+1;
      	   else
           sdataout=sdataout-1;
     end
  assign dataout=sdataout;
endmodule

counter_assertion_inline/testbench.sv
  module test_counter;
    logic clk,rst_n,ld_en,updwn,en;
    logic[7:0] datain;
    wire [7:0] dataout;
    
   property counter_reset;
     @(clk) if(!rst_n) dataout==8'b0;
   endproperty
  
   property counter_DOWN_count;
     @(posedge clk) if(!rst_n &ld_en & en)
       if(!updwn)##1 (dataout-8'h01)==$past(dataout); 
  endproperty
    
   property counter_UP_count;
     @(posedge clk) if(!rst_n &ld_en & en)
       if(updwn)##1 (dataout+8'h01)==$past(dataout);
  endproperty
  
          	
  counter8b u1(.clk(clk),
               .rst_n(rst_n),
               .ld_en(ld_en),
               .updwn(updwn),
               .en(en),
               .datain(datain),
               .dataout(dataout)
              );
      
          

    initial
    begin
      clk=1'b0;
      forever #5 clk=~clk;
	end
    
    initial 
    begin
	       rst_n=1'b1; ld_en=1'b0;            en=1'b0;
               
	  #20; rst_n=1'b0; ld_en=1'b0;            en=1'b0;
      counter_reset_check:assert property(counter_reset)
        $display($stime,,,"\t COUNTER RESET CHECK PASS WTIH rst_n=%b dataout=%0d",rst_n,dataout);
      else
        $display($stime,,,"\t COUNTER RESET CHECK FAIL WITH rst_n=%b dataout=%0d",rst_n,dataout);
      
      #20; rst_n=1'b1; ld_en=1'b1;datain=8'h64; 
      #20; if(rst_n==1'b1 && ld_en==1'b1)
           assert(dataout==datain)
             $display($stime,,,"\t COUNTER PRELOAD CHECK PASS WTIH datain=%b dataout=%0d",datain,dataout);
           else
             $display($stime,,,"\t COUNTER PRELOAD CHECK FAIL WITH datain=%b dataout=%0d",datain,dataout);
              
                       ld_en=1'b0;            en=1'b1; updwn=1'b0;
      #10; 
      counter_count_check:assert property(counter_DOWN_count)
        $display($stime,,,"\t COUNTER COUNT CHECK PASS::DOWN COUNT USING USING $past \n");
 	  else
        $display($stime,,,"\t COUNTER COUNT CHECK FAIL::DOWN COUNT USING USING $past \n");
      #50;											   updwn=1'b1; 
      #10;
      counter_count_check2:assert property(counter_UP_count)
        $display($stime,,,"\t COUNTER COUNT CHECK PASS::UP COUNT USING USING $past \n");
 	  else
        $display($stime,,,"\t COUNTER COUNT CHECK FAIL::UP COUNT USING USING $past \n");
       
      #50;            ld_en=1'b1;			  en=1'b0;
         
              
      #20;
      $finish(2);                
    end
 		
    always @(posedge clk)
    begin
      $display($stime,,,"rst_n=%b clk=%b en=%b ld_en=%b updwn=%b DIN=%0d Dout=%0d",rst_n,clk,en,ld_en,updwn,datain,dataout);
    end
         
        
    initial
    begin
      $dumpfile("counter.vcd");
      $dumpvars(1);
    end

          
endmodule

counter_assertion_inline/counter.vcd
$date
Sat Nov 28 02:09:50 2020
$end
$version
Riviera-PRO Version 2020.04.130.7729
$end
$timescale
1 ns
$end

$scope module test_counter $end
$var wire 8 ! dataout [7:0] $end
$var reg 1 " clk $end
$var reg 1 # rst_n $end
$var reg 1 $ ld_en $end
$var reg 1 % updwn $end
$var reg 1 & en $end
$var reg 8 ' datain [7:0] $end
$upscope $end

$enddefinitions $end
$dumpvars
bx !
0"
1#
0$
x%
0&
bx '
$end
#5
1"
#10
0"
#15
1"
#20
0#
0"
b0 !
#25
1"
#30
0"
#35
1"
#40
1#
1$
b1100100 '
0"
#45
1"
b1100100 !
#50
0"
#55
1"
#60
0$
1&
0%
0"
#65
1"
b1100011 !
#70
0"
#75
1"
b1100010 !
#80
0"
#85
1"
b1100001 !
#90
0"
#95
1"
b1100000 !
#100
0"
#105
1"
b1011111 !
#110
0"
#115
1"
b1011110 !
#120
1%
0"
#125
1"
b1011111 !
#130
0"
#135
1"
b1100000 !
#140
0"
#145
1"
b1100001 !
#150
0"
#155
1"
b1100010 !
#160
0"
#165
1"
b1100011 !
#170
0"
#175
1"
b1100100 !
#180
1$
0&
0"
