counter_assertion_property/binding_file.sv


module binding_module();
  bind counter8b counter_property asset_prop(.clk(clk),
                                             .rst_n(rst_n),
                                             .ld_en(ld_en),
                                             .updwn(updwn),
                                             .en(en),
                                             .datain(datain),
                                             .dataout(dataout)
                                            );
  
endmodule

counter_assertion_property/counter_property.sv


module counter_property(input clk,rst_n,ld_en,updwn,en, input [7:0]datain,output [7:0]dataout);

  
  property counter_reset;
    @(clk) if(!rst_n) dataout==8'b0;
  endproperty
    
  property counter_load;
    @(posedge clk) if(rst_n & ld_en) (dataout == datain);
  endproperty
  
  property counter_DOWN_count;
    @(posedge clk) if(rst_n &!ld_en & en)
      if(updwn)##1 (dataout-1'b1)==$past(dataout);
    //else ##1 (dataout+8'h01)==$past(dataout);
  endproperty
  
  property counter_UP_count;
    @(posedge clk) if(rst_n & !ld_en & en)
      if(!updwn)##1 (dataout-1'b1)==$past(dataout);
    //else ##1 (dataout+8'h01)==$past(dataout);
  endproperty
  
  initial
  begin
    #20; 
    counter_reset_check:assert property(counter_reset)
      $display($stime,,,"\t COUNTER RESET CHECK PASS WTIH rst_n=%b dataout=%0d",rst_n,dataout);
   	else
      $display($stime,,,"\t COUNTER RESET CHECK FAIL WITH rst_n=%b dataout=%0d",rst_n,dataout);
        
    #10;      
    counter_load_check:assert property(counter_load)
      $display($stime,,,"\t COUNTER PRELOAD CHECK PASS WTIH rst_n=%b dataout=%0d",rst_n,$past(dataout));
    else
      $display($stime,,,"\t COUNTER PRELOAD CHECK FAIL WITH rst_n=%b dataout=%0d",rst_n,$past(dataout));
          
    #60;
    counter_count_check:assert property(counter_DOWN_count)
      $display($stime,,,"\t COUNTER COUNT CHECK PASS::DOWN COUNT USING $past \n");
 	else
      $display($stime,,,"\t COUNTER COUNT CHECK FAIL::DOWN COUNT USING $past \n");
  
   #90;
    counter_count_check2:assert property(counter_UP_count)
      $display($stime,,,"\t COUNTER COUNT CHECK PASS::UP COUNT USING $past \n");
 	else
      $display($stime,,,"\t COUNTER COUNT CHECK FAIL::UP COUNT USING $past \n");   
    
    end
      
endmodule

counter_assertion_property/design.sv
// Code your design here
//`timescale 1ns/ 1ps;
module counter8b (clk,rst_n,ld_en,updwn,en,datain,dataout);
  
  input clk, rst_n,ld_en,updwn,en;           
  input  [7:0] datain;
  output [7:0] dataout;
  reg    [7:0] sdataout;
  
  always @(posedge clk or negedge rst_n)
    begin
      if(!rst_n)
        sdataout=8'b0;
    else if(ld_en)
          sdataout=datain; 
    else if(!en)
          sdataout=sdataout;
    else if (updwn)
       	   sdataout=sdataout+1;
      	   else
           sdataout=sdataout-1;
     end
  assign dataout=sdataout;
endmodule

counter_assertion_property/testbench.sv
// Code your testbench here
// or browse Examples
`include "counter_property.sv"
`include "binding_file.sv"

module tester;
  reg clk,rst_n,ld_en,updwn,en;
  reg [7:0] datain;
  wire [7:0] dataout;
  
  
  
  /* bind counter8b counter_property inst(.clk(clk),
                                       .rst_n(rst_n),
                                       .ld_en(ld_en),
                                       .updwn(updwn),
                                       .en(en),
                                       .datain(datain),
                                       .dataout(dataout)
                                      );
  */
  
  initial
  begin
      clk = 1'b1;
      rst_n=1'b1;      
      forever #5  clk = ~clk;
  end
  
  initial 
  begin
        rst_n=1'b1;ld_en=1'b1; datain=8'd255; updwn=1'b1;en=1'b1;
    #20;rst_n=1'b0;ld_en=1'b0; datain=8'd0;   updwn=1'b0;en=1'b0;
    #10;rst_n=1'b1;ld_en=1'b0; datain=8'd0;   updwn=1'b1;en=1'b1;
    #20;           ld_en=1'b0;
    #30;                                      updwn=1'b1;en=1'b1;              
    #40;          ld_en=1'b0;                updwn=1'b0;en=1'b0;
    #50;          ld_en=1'b1; datain=8'd63;  updwn=1'b0;en=1'b1;
    #10;           ld_en=1'b0;                updwn=1'b1;en=1'b1;       
    #100;                                                en=1'b0;
    #50;
    $finish(2);
    end
  
  counter8b DUT(.clk(clk),
                .rst_n(rst_n),
                .ld_en(ld_en),
                .updwn(updwn),
                .en(en),
                .datain(datain),
                .dataout(dataout)
               );
  
  always @ (posedge clk)
  begin
    $display("%t Load_en:%d, Up_down:%d,en:%d, Datain:%d, Data_out:%d",$time,ld_en,updwn,en,datain,dataout);
  end
  
  initial
    begin
      $dumpfile("counter.vcd");
      $dumpvars(1);
    end
  
endmodule

counter_assertion_property/counter.vcd
$date
Sat Nov 28 02:11:15 2020
$end
$version
Riviera-PRO Version 2020.04.130.7729
$end
$timescale
1 ns
$end

$scope module binding_module $end
$upscope $end


$scope module tester $end
$var wire 8 ! dataout [7:0] $end
$var reg 1 " clk $end
$var reg 1 # rst_n $end
$var reg 1 $ ld_en $end
$var reg 1 % updwn $end
$var reg 1 & en $end
$var reg 8 ' datain [7:0] $end
$upscope $end

$enddefinitions $end
$dumpvars
b11111111 !
1"
1#
1$
1%
1&
b11111111 '
$end
#5
0"
#10
1"
#15
0"
#20
0#
0$
b0 '
0%
0&
1"
b0 !
#25
0"
#30
1#
1%
1&
1"
b1 !
#35
0"
#40
1"
b10 !
#45
0"
#50
1"
b11 !
#55
0"
#60
1"
b100 !
#65
0"
#70
1"
b101 !
#75
0"
#80
1"
b110 !
#85
0"
#90
1"
b111 !
#95
0"
#100
1"
b1000 !
#105
0"
#110
1"
b1001 !
#115
0"
#120
0%
0&
1"
#125
0"
#130
1"
#135
0"
#140
1"
#145
0"
#150
1"
#155
0"
#160
1"
#165
0"
#170
1$
b111111 '
1&
1"
b111111 !
#175
0"
#180
0$
1%
1"
b1000000 !
#185
0"
#190
1"
b1000001 !
#195
0"
#200
1"
b1000010 !
#205
0"
#210
1"
b1000011 !
#215
0"
#220
1"
b1000100 !
#225
0"
#230
1"
b1000101 !
#235
0"
#240
1"
b1000110 !
#245
0"
#250
1"
b1000111 !
#255
0"
#260
1"
b1001000 !
#265
0"
#270
1"
b1001001 !
#275
0"
#280
0&
1"
